ananxw_jumpin_allin1f.py
builtin_plugins.py
ananxw_jumpin/LICENSE
ananxw_jumpin/NOTICE
ananxw_jumpin/README.md
ananxw_jumpin/__init__.py
ananxw_jumpin/ananxw_jumpin_allin1f.py
ananxw_jumpin/builtin_plugins.py
ananxw_jumpin/requirements.txt
ananxw_jumpin/readme_ref_res/base_ui1.png
ananxw_jumpin/readme_ref_res/chathistory_memory_ex_ui1.png
ananxw_jumpin/readme_ref_res/ollama_ex_ui1.png
ananxw_jumpin-0.7.0.dist-info/LICENSE
ananxw_jumpin-0.7.0.dist-info/METADATA
ananxw_jumpin-0.7.0.dist-info/NOTICE
ananxw_jumpin-0.7.0.dist-info/WHEEL
ananxw_jumpin-0.7.0.dist-info/top_level.txt
ananxw_jumpin-0.7.0.dist-info/RECORD
