Metadata-Version: 2.1
Name: ananxw_jumpin
Version: 0.7.0
Summary: ANAN Jumpin - AI Performance Tools and Platform
Home-page: https://github.com/wfeng007/ananxw_jumpin
Author: wfeng007
Author-email: wfeng007@163.com
License: Apache License 2.0
Classifier: Programming Language :: Python :: 3
Classifier: License :: OSI Approved :: Apache Software License
Classifier: Operating System :: OS Independent
Requires-Python: >=3.9
License-File: LICENSE
License-File: NOTICE
Requires-Dist: python-dotenv==1.0.1
Requires-Dist: pyyaml==6.0.2
Requires-Dist: PySide6==6.7.2
Requires-Dist: pynput==1.7.3
Requires-Dist: markdown==3.3.6
Requires-Dist: openai==1.42.0
Requires-Dist: langchain==0.3.0
Requires-Dist: langchain-openai==0.2.2
Requires-Dist: langchain-community==0.3.0
Requires-Dist: langchain-chroma==0.1.4
Requires-Dist: pymupdf==1.24.10
Requires-Dist: httpx==0.27.0
Requires-Dist: typing-extensions==4.12.2; python_version < "3.12"
